deptry_auto/__init__.py
deptry_auto/__main__.py
deptry_auto/bootstrap.py
deptry_auto-0.3.9.dist-info/WHEEL
deptry_auto-0.3.9.dist-info/entry_points.txt
deptry_auto-0.3.9.dist-info/METADATA
deptry_auto-0.3.9.dist-info/RECORD
