Metadata-Version: 2.3
Name: deptry-auto
Version: 0.3.9
Summary: Automatically add missing dependencies found by deptry using uv.
Author: Matthew Muller
Author-email: Matthew Muller <matthew.muller@uon.edu.au>
Requires-Dist: deptry>=0.24.0
Requires-Python: >=3.14
